src/nebari_plugin_ray/__about__.py
src/nebari_plugin_ray/__init__.py
src/nebari_plugin_ray/plugin.py
src/nebari_plugin_ray/template/ingress.tf
src/nebari_plugin_ray/template/main.tf
src/nebari_plugin_ray/template/outputs.tf
src/nebari_plugin_ray/template/patch.tf
src/nebari_plugin_ray/template/s3.tf
src/nebari_plugin_ray/template/variables.tf
src/nebari_plugin_ray/template/versions.tf
src/nebari_plugin_ray/template/chart/ray-cluster/.helmignore
src/nebari_plugin_ray/template/chart/ray-cluster/Chart.yaml
src/nebari_plugin_ray/template/chart/ray-cluster/values.yaml
src/nebari_plugin_ray/template/chart/ray-cluster/templates/_helpers.tpl
src/nebari_plugin_ray/template/chart/ray-cluster/templates/raycluster-cluster.yaml
nebari_plugin_ray-0.0.3.dist-info/METADATA
nebari_plugin_ray-0.0.3.dist-info/WHEEL
nebari_plugin_ray-0.0.3.dist-info/entry_points.txt
nebari_plugin_ray-0.0.3.dist-info/licenses/LICENSE
nebari_plugin_ray-0.0.3.dist-info/RECORD
