Metadata-Version: 2.1
Name: nebari-plugin-ray
Version: 0.0.3
Summary: MetroStar Onyx - Ray plugin for Nebari platform
Project-URL: Documentation, https://github.com/MetroStar/nebari-ray#readme
Project-URL: Issues, https://github.com/MetroStar/nebari-ray/issues
Project-URL: Source, https://github.com/MetroStar/nebari-ray
Author-email: Scott Blair <sblair@metrostar.com>
License-Expression: Apache-2.0
License-File: LICENSE
Classifier: Development Status :: 4 - Beta
Classifier: Programming Language :: Python
Classifier: Programming Language :: Python :: 3.10
Classifier: Programming Language :: Python :: 3.11
Classifier: Programming Language :: Python :: Implementation :: CPython
Classifier: Programming Language :: Python :: Implementation :: PyPy
Requires-Python: >=3.10
Requires-Dist: nebari
